openvino/__init__.py
openvino/_pyopenvino.cpython-39-aarch64-linux-gnu.so
openvino/utils.py
openvino/_offline_transformations/__init__.py
openvino/cmake/OpenVINOConfig-version.cmake
openvino/cmake/OpenVINOConfig.cmake
openvino/cmake/OpenVINOTargets-release.cmake
openvino/cmake/OpenVINOTargets.cmake
openvino/cmake/TBBConfig.cmake
openvino/cmake/TBBConfigVersion.cmake
openvino/cmake/TBBTargets-release.cmake
openvino/cmake/TBBTargets.cmake
openvino/experimental/__init__.py
openvino/frontend/__init__.py
openvino/frontend/frontend.py
openvino/frontend/jax/__init__.py
openvino/frontend/jax/jaxpr_decoder.py
openvino/frontend/jax/passes.py
openvino/frontend/jax/py_jax_frontend.cpython-39-aarch64-linux-gnu.so
openvino/frontend/jax/utils.py
openvino/frontend/onnx/__init__.py
openvino/frontend/onnx/py_onnx_frontend.cpython-39-aarch64-linux-gnu.so
openvino/frontend/paddle/__init__.py
openvino/frontend/paddle/py_paddle_frontend.cpython-39-aarch64-linux-gnu.so
openvino/frontend/pytorch/__init__.py
openvino/frontend/pytorch/fx_decoder.py
openvino/frontend/pytorch/gptq.py
openvino/frontend/pytorch/module_extension.py
openvino/frontend/pytorch/patch_model.py
openvino/frontend/pytorch/py_pytorch_frontend.cpython-39-aarch64-linux-gnu.so
openvino/frontend/pytorch/ts_decoder.py
openvino/frontend/pytorch/utils.py
openvino/frontend/pytorch/torchdynamo/backend.py
openvino/frontend/pytorch/torchdynamo/backend_utils.py
openvino/frontend/pytorch/torchdynamo/compile.py
openvino/frontend/pytorch/torchdynamo/decompositions.py
openvino/frontend/pytorch/torchdynamo/execute.py
openvino/frontend/pytorch/torchdynamo/op_support.py
openvino/frontend/pytorch/torchdynamo/partition.py
openvino/frontend/tensorflow/__init__.py
openvino/frontend/tensorflow/graph_iterator.py
openvino/frontend/tensorflow/node_decoder.py
openvino/frontend/tensorflow/py_tensorflow_frontend.cpython-39-aarch64-linux-gnu.so
openvino/frontend/tensorflow/utils.py
openvino/helpers/__init__.py
openvino/helpers/packing.py
openvino_nightly-2024.5.0.dev20241105.dist-info/LICENSE
openvino_nightly-2024.5.0.dev20241105.dist-info/METADATA
openvino_nightly-2024.5.0.dev20241105.dist-info/WHEEL
openvino_nightly-2024.5.0.dev20241105.dist-info/entry_points.txt
openvino_nightly-2024.5.0.dev20241105.dist-info/onednn_third-party-programs.txt
openvino_nightly-2024.5.0.dev20241105.dist-info/onetbb_third-party-programs.txt
openvino_nightly-2024.5.0.dev20241105.dist-info/readme.txt
openvino_nightly-2024.5.0.dev20241105.dist-info/runtime-third-party-programs.txt
openvino_nightly-2024.5.0.dev20241105.dist-info/top_level.txt
openvino_nightly-2024.5.0.dev20241105.dist-info/RECORD
