Metadata-Version: 2.1
Name: openvino-nightly
Version: 2024.5.0.dev20241105
Summary: OpenVINO(TM) Runtime
Home-page: https://docs.openvino.ai/nightly/index.html
Download-URL: https://github.com/openvinotoolkit/openvino/releases
Author: Intel(R) Corporation
Author-email: openvino@intel.com
License: OSI Approved :: Apache Software License
License-File: readme.txt
License-File: ../../../../licensing/runtime-third-party-programs.txt
License-File: ../../../../licensing/onetbb_third-party-programs.txt
License-File: ../../../../licensing/onednn_third-party-programs.txt
License-File: ../../../../LICENSE
Requires-Dist: numpy <2.2.0,>=1.16.6
Requires-Dist: openvino-telemetry >=2023.2.1
Requires-Dist: packaging
